mcp_open_data_hk/__init__.py
mcp_open_data_hk/__main__.py
mcp_open_data_hk/server.py
mcp_open_data_hk-0.2.3.dist-info/licenses/LICENSE
mcp_open_data_hk-0.2.3.dist-info/METADATA
mcp_open_data_hk-0.2.3.dist-info/WHEEL
mcp_open_data_hk-0.2.3.dist-info/entry_points.txt
mcp_open_data_hk-0.2.3.dist-info/top_level.txt
mcp_open_data_hk-0.2.3.dist-info/RECORD
