Metadata-Version: 2.4
Name: mcp-open-data-hk
Version: 0.2.3
Summary: MCP server for accessing data.gov.hk open data
Author-email: Tony Chan <chankwongyintony@gmail.com>
License: MIT
Project-URL: Homepage, https://github.com/mcp-open-data-hk/mcp-open-data-hk
Project-URL: Repository, https://github.com/mcp-open-data-hk/mcp-open-data-hk
Project-URL: Issues, https://github.com/mcp-open-data-hk/mcp-open-data-hk/issues
Classifier: Development Status :: 3 - Alpha
Classifier: Intended Audience :: Developers
Classifier: License :: OSI Approved :: MIT License
Classifier: Programming Language :: Python :: 3
Classifier: Programming Language :: Python :: 3.10
Classifier: Programming Language :: Python :: 3.11
Classifier: Programming Language :: Python :: 3.12
Requires-Python: >=3.10
License-File: LICENSE
Requires-Dist: fastmcp>=0.1.0
Requires-Dist: httpx>=0.27.0
Provides-Extra: test
Requires-Dist: pytest>=6.0; extra == "test"
Requires-Dist: pytest-asyncio>=0.14.0; extra == "test"
Provides-Extra: dev
Requires-Dist: black>=22.0; extra == "dev"
Requires-Dist: flake8>=4.0; extra == "dev"
Dynamic: license-file
